ff_ebook/__init__.py
ff_ebook/ffnet.py
ff_ebook-0.4.1.dist-info/WHEEL
ff_ebook-0.4.1.dist-info/METADATA
ff_ebook-0.4.1.dist-info/RECORD
