Metadata-Version: 2.1
Name: ff-ebook
Version: 0.4.1
Summary: Ebook generator for fanfiction sites.
Author: Neia Neutuladh, Michal Hozza
Requires-Python: >=3.8,<4.0
Classifier: Programming Language :: Python :: 3
Classifier: Programming Language :: Python :: 3.10
Classifier: Programming Language :: Python :: 3.8
Classifier: Programming Language :: Python :: 3.9
Requires-Dist: beautifulsoup4 (>=4.9.1,<5.0.0)
Requires-Dist: cloudscraper (>=1.2.58,<2.0.0)
Requires-Dist: requests (>=2.24.0,<3.0.0)
